coh2_live_stats/__init__.py
coh2_live_stats/__main__.py
coh2_live_stats/_coh2livestats.toml
coh2_live_stats/_logging.toml
coh2_live_stats/coh2api.py
coh2_live_stats/logging_conf.py
coh2_live_stats/output.py
coh2_live_stats/py.typed
coh2_live_stats/settings.py
coh2_live_stats/util.py
coh2_live_stats/version.py
coh2_live_stats/data/__init__.py
coh2_live_stats/data/color.py
coh2_live_stats/data/countries.py
coh2_live_stats/data/faction.py
coh2_live_stats/data/match.py
coh2_live_stats/data/player.py
coh2_live_stats/data/team.py
coh2_live_stats/res/coh2_live_stats.ico
coh2_live_stats/res/coh2_live_stats.xcf
coh2_live_stats/res/coh2_live_stats_64.png
coh2_live_stats/res/example_0.svg
coh2_live_stats/res/example_1.svg
coh2_live_stats/res/example_default.svg
coh2_live_stats/res/horn.wav
coh2_live_stats/res/horn_epic.wav
coh2_live_stats/res/horn_subtle.wav
coh2_live_stats-1.2.4.dist-info/COPYING
coh2_live_stats-1.2.4.dist-info/METADATA
coh2_live_stats-1.2.4.dist-info/WHEEL
coh2_live_stats-1.2.4.dist-info/entry_points.txt
coh2_live_stats-1.2.4.dist-info/top_level.txt
coh2_live_stats-1.2.4.dist-info/RECORD
