Metadata-Version: 2.1
Name: coh2_live_stats
Version: 1.2.4
Summary: Show player and team stats of a currently played, replayed or last played Company of Heroes 2 match.
Author-email: Andreas Becker <brofi.archlinux@gmail.com>
License: GNU GENERAL PUBLIC LICENSE
Project-URL: Homepage, https://github.com/brofi/coh2-live-stats
Project-URL: Documentation, https://github.com/brofi/coh2-live-stats
Project-URL: Issues, https://github.com/brofi/coh2-live-stats/issues
Project-URL: Source, https://github.com/brofi/coh2-live-stats
Keywords: CoH2,Company of Heroes 2
Classifier: Environment :: Console
Classifier: License :: OSI Approved :: GNU General Public License v3 or later (GPLv3+)
Classifier: Natural Language :: English
Classifier: Programming Language :: Python :: 3
Classifier: Programming Language :: Python :: 3 :: Only 
Classifier: Programming Language :: Python :: 3.12
Classifier: Operating System :: Microsoft :: Windows
Classifier: Operating System :: POSIX :: Linux
Classifier: Topic :: Games/Entertainment :: Real Time Strategy
Requires-Python: >=3.12
License-File: COPYING
Requires-Dist: colorama >=0.4.6
Requires-Dist: httpx >=0.27.0
Requires-Dist: prettytable >=3.10.0
Requires-Dist: pydantic-settings >=2.2.1
Requires-Dist: watchdog >=4.0.0
Provides-Extra: build
Requires-Dist: build >=1.2.1 ; extra == 'build'
Requires-Dist: invoke >=2.2.0 ; extra == 'build'
Requires-Dist: mypy >=1.10.0 ; extra == 'build'
Requires-Dist: pyinstaller >=6.6.0 ; extra == 'build'
Requires-Dist: pytest >=8.1.1 ; extra == 'build'
Requires-Dist: pytest-asyncio >=0.23.6 ; extra == 'build'
Requires-Dist: respx >=0.21.1 ; extra == 'build'
Requires-Dist: tomlkit >=0.12.4 ; extra == 'build'
Requires-Dist: twine >=5.0.0 ; extra == 'build'
Provides-Extra: dev
Requires-Dist: ruff >=0.4.1 ; extra == 'dev'
Requires-Dist: pre-commit >=3.7.0 ; extra == 'dev'
